counterz/__init__.py
counterz-0.0.2.dist-info/LICENSE
counterz-0.0.2.dist-info/METADATA
counterz-0.0.2.dist-info/WHEEL
counterz-0.0.2.dist-info/top_level.txt
counterz-0.0.2.dist-info/RECORD
